<?xml version="1.0" encoding="UTF-8"?>
<mdsystem>
	<general>
		<normdataFile>config/mdsystem/export_normdata_clean_130112.rdf</normdataFile>
	</general>
	<converter>
		<templates>		
			<eDoc>
				<templatePath>config/convert2rdf/eDocToRdfTemplate.xml</templatePath>
			</eDoc>
		</templates>
		<xslt>
			<mods>
				<stylesheetPath>config/convert2rdf/modstordf.xsl</stylesheetPath>
			</mods>
			<mets>
				<stylesheetPath>config/convert2rdf/metstordf.xsl</stylesheetPath>
			</mets>
		</xslt>
	</converter>
	<rdfmanager>
		<tripleStore>
			<datasetPath>save/wspRdfStore</datasetPath>
			<larqIndexPath>save/larqindex</larqIndexPath>
		</tripleStore>
	</rdfmanager>
</mdsystem>